aiodabpumps/__init__.py
aiodabpumps/dabpumps_api.py
aiodabpumps/dabpumps_client.py
aiodabpumps/dabpumps_const.py
aiodabpumps/dabpumps_data.py
aiodabpumps-1.1.1.dist-info/licenses/LICENSE
aiodabpumps-1.1.1.dist-info/METADATA
aiodabpumps-1.1.1.dist-info/WHEEL
aiodabpumps-1.1.1.dist-info/top_level.txt
aiodabpumps-1.1.1.dist-info/RECORD
